eavesdropper/__init__.py
eavesdropper/core.py
eavesdropper/utils.py
eavesdropper/__metadata__/LICENSE
eavesdropper/__metadata__/README.md
eavesdropper/__metadata__/__init__.py
eavesdropper/__metadata__/requirements.txt
eavesdropper/pkg_data/__init__.py
eavesdropper/pkg_data/mitmproxy/LICENSE
eavesdropper/pkg_data/mitmproxy/__init__.py
eavesdropper/pkg_data/mitmproxy/addonmanager.py
eavesdropper/pkg_data/mitmproxy/certs.py
eavesdropper/pkg_data/mitmproxy/command.py
eavesdropper/pkg_data/mitmproxy/command_lexer.py
eavesdropper/pkg_data/mitmproxy/connections.py
eavesdropper/pkg_data/mitmproxy/controller.py
eavesdropper/pkg_data/mitmproxy/ctx.py
eavesdropper/pkg_data/mitmproxy/eventsequence.py
eavesdropper/pkg_data/mitmproxy/exceptions.py
eavesdropper/pkg_data/mitmproxy/flow.py
eavesdropper/pkg_data/mitmproxy/flowfilter.py
eavesdropper/pkg_data/mitmproxy/http.py
eavesdropper/pkg_data/mitmproxy/log.py
eavesdropper/pkg_data/mitmproxy/master.py
eavesdropper/pkg_data/mitmproxy/options.py
eavesdropper/pkg_data/mitmproxy/optmanager.py
eavesdropper/pkg_data/mitmproxy/py.typed
eavesdropper/pkg_data/mitmproxy/stateobject.py
eavesdropper/pkg_data/mitmproxy/tcp.py
eavesdropper/pkg_data/mitmproxy/types.py
eavesdropper/pkg_data/mitmproxy/version.py
eavesdropper/pkg_data/mitmproxy/websocket.py
eavesdropper/pkg_data/mitmproxy/addons/__init__.py
eavesdropper/pkg_data/mitmproxy/addons/anticache.py
eavesdropper/pkg_data/mitmproxy/addons/anticomp.py
eavesdropper/pkg_data/mitmproxy/addons/asgiapp.py
eavesdropper/pkg_data/mitmproxy/addons/block.py
eavesdropper/pkg_data/mitmproxy/addons/browser.py
eavesdropper/pkg_data/mitmproxy/addons/check_ca.py
eavesdropper/pkg_data/mitmproxy/addons/clientplayback.py
eavesdropper/pkg_data/mitmproxy/addons/command_history.py
eavesdropper/pkg_data/mitmproxy/addons/core.py
eavesdropper/pkg_data/mitmproxy/addons/cut.py
eavesdropper/pkg_data/mitmproxy/addons/disable_h2c.py
eavesdropper/pkg_data/mitmproxy/addons/dumper.py
eavesdropper-0.5.1.dist-info/METADATA
eavesdropper-0.5.1.dist-info/WHEEL
eavesdropper-0.5.1.dist-info/top_level.txt
eavesdropper-0.5.1.dist-info/RECORD
