Metadata-Version: 2.1
Name: eavesdropper
Version: 0.5.1
Summary: Eavesdropper, an application-level gateway firewall proxy, gives you control over all network traffic. Or simply use its integrated mitmproxy 5.3.0 which can be completely controlled with Python code.
Home-page: http://code.foxe6.kozow.com/eavesdropper/
Author: f̣ộx̣ệ6
Author-email: foxe6@pm.me
License: AGPL-3.0
Project-URL: Sourcecode, http://code.foxe6.kozow.com/eavesdropper.zip
Project-URL: Documentation, http://code.foxe6.kozow.com/eavesdropper/test/
Project-URL: Example, http://code.foxe6.kozow.com/eavesdropper/eavesdropper/example/
Project-URL: Funding, https://paypal.me/foxe6
Project-URL: Say Thanks!, https://saythanks.io/to/foxe6
Keywords: eavesdropper proxy mitm request response network traffic firewall monitor intercept manipulate modify change content headers
Platform: UNKNOWN
Classifier: Programming Language :: Python :: 3.9
Classifier: Topic :: Utilities
Classifier: Natural Language :: English
Classifier: Intended Audience :: Developers
Classifier: License :: OSI Approved :: GNU Affero General Public License v3
Classifier: Operating System :: MacOS
Classifier: Operating System :: POSIX
Classifier: Operating System :: Microsoft :: Windows :: Windows 10
Classifier: Development Status :: 5 - Production/Stable
Requires-Python: >=3.5
Requires-Dist: omnitools (>=0.0.1)
Requires-Dist: Brotli (>=0.0.1)
Requires-Dist: ldap3 (>=0.0.1)
Requires-Dist: pyperclip (>=0.0.1)
Requires-Dist: hyperframe (>=0.0.1)
Requires-Dist: protobuf (>=0.0.1)
Requires-Dist: pyOpenSSL (>=0.0.1)
Requires-Dist: sortedcontainers (>=0.0.1)
Requires-Dist: pyparsing (>=0.0.1)
Requires-Dist: certifi (>=0.0.1)
Requires-Dist: flask (>=0.0.1)
Requires-Dist: kaitaistruct (>=0.0.1)
Requires-Dist: urwid (>=0.0.1)
Requires-Dist: wsproto (>=0.0.1)
Requires-Dist: pyasn1 (>=0.0.1)
Requires-Dist: zstandard (>=0.0.1)
Requires-Dist: msgpack (>=0.0.1)
Requires-Dist: pydivert (>=0.0.1)
Requires-Dist: click (>=0.0.1)
Requires-Dist: publicsuffix2 (>=0.0.1)
Requires-Dist: h2 (>=0.0.1)
Requires-Dist: blinker (>=0.0.1)
Requires-Dist: cryptography (>=0.0.1)
Requires-Dist: asgiref (>=0.0.1)
Requires-Dist: ruamel.yaml (>=0.0.1)
Requires-Dist: passlib (>=0.0.1)
Requires-Dist: tornado (>=0.0.1)
Requires-Dist: cffi (>=0.0.1)
Requires-Dist: six (>=0.0.1)
Requires-Dist: Werkzeug (>=0.0.1)
Requires-Dist: Jinja2 (>=0.0.1)
Requires-Dist: itsdangerous (>=0.0.1)
Requires-Dist: hpack (>=0.0.1)
Requires-Dist: setuptools (>=0.0.1)
Requires-Dist: ruamel.yaml.clib (>=0.0.1)
Requires-Dist: h11 (>=0.0.1)
Requires-Dist: pycparser (>=0.0.1)
Requires-Dist: MarkupSafe (>=0.0.1)
